pys/__init__.py
pys-0.0.14.post4.dist-info/LICENSE.md
pys-0.0.14.post4.dist-info/METADATA
pys-0.0.14.post4.dist-info/WHEEL
pys-0.0.14.post4.dist-info/top_level.txt
pys-0.0.14.post4.dist-info/RECORD
