Metadata-Version: 2.1
Name: pys
Version: 0.0.14.post4
Summary: Miscellaneous Pythons
Home-page: http://github.com/noobermin/pys
Author: noobermin
Author-email: ngirmang.1@osu.com
License: MIT
Platform: UNKNOWN
